podcastindex33/__init__.py
podcastindex33/core.py
podcastindex33/run.py
podcastindex33-0.2.0.dist-info/entry_points.txt
podcastindex33-0.2.0.dist-info/WHEEL
podcastindex33-0.2.0.dist-info/METADATA
podcastindex33-0.2.0.dist-info/LICENSE
podcastindex33-0.2.0.dist-info/RECORD
