Metadata-Version: 2.1
Name: podcastindex33
Version: 0.2.0
Summary: Wrapper around the Podcast Index 2.0 API
License: MIT
Author-email: Paul Bailey <paul@neutron.studio>
Requires-Python: >=3.7
Classifier: License :: OSI Approved :: MIT License
Classifier: Programming Language :: Python :: 3
Classifier: Programming Language :: Python :: 3.7
Classifier: Programming Language :: Python :: 3.8
Classifier: Programming Language :: Python :: 3.9
Requires-Dist: httpx~=0.18
Requires-Dist: typer~=0.3
Project-URL: homepage, https://github.com/pizzapanther/podcastindex33
